{
  "db_name": "PostgreSQL",
  "query": "SELECT id, name, siret, created_at FROM public.companies ORDER BY created_at DESC",
  "describe": {
    "columns": [
      {
        "ordinal": 0,
        "name": "id",
        "type_info": "Uuid"
      },
      {
        "ordinal": 1,
        "name": "name",
        "type_info": "Text"
      },
      {
        "ordinal": 2,
        "name": "siret",
        "type_info": "Text"
      },
      {
        "ordinal": 3,
        "name": "created_at",
        "type_info": "Timestamptz"
      }
    ],
    "parameters": {
      "Left": []
    },
    "nullable": [
      false,
      false,
      true,
      false
    ]
  },
  "hash": "cd8a7560e27b4b2025692240b3dcc5dd40d71a7a9d4e4d2fa637fb116226b265"
}
